LICENSE.md
README.md
setup.py
corvus/__init__.py
corvus/app.py
corvus/client.py
corvus/errors.py
corvus/jsonrpc.py
corvus/methods.py
corvus/request.py
corvus/utils.py
corvus.egg-info/PKG-INFO
corvus.egg-info/SOURCES.txt
corvus.egg-info/dependency_links.txt
corvus.egg-info/requires.txt
corvus.egg-info/top_level.txt
corvus.egg-info/zip-safe